README.rst
setup.py
hsdecks/__init__.py
hsdecks/hsdecks.py
hsdecks.egg-info/PKG-INFO
hsdecks.egg-info/SOURCES.txt
hsdecks.egg-info/dependency_links.txt
hsdecks.egg-info/entry_points.txt
hsdecks.egg-info/requires.txt
hsdecks.egg-info/top_level.txt