Metadata-Version: 1.0
Name: hsdecks
Version: 0.6.0
Summary: Hearthstone deck tool
Home-page: https://github.com/pdrb/hsdecks
Author: Pedro Buteri Gonring
Author-email: pedro@bigode.net
License: MIT
Keywords: hs hearthstone deck tool
Platform: UNKNOWN
